{"title": "SF Sort", "description": "Sort a float/complex vector by absolute values", "authors": [{"name": "Matheus Farias Barbosa", "email": "m230888@dac.unicamp.br", "institution": "University of Campinas"}], "tags": ["rsf", "madagascar", "editing, sorting and manipulation"], "programs": [{"enabled": true, "program": {"title": "SF Sort", "description": "Sort a float/complex vector by absolute values", "authors": [{"name": "Gilles Hennenfent", "institution": "UBC"}, {"name": "Henryk Modzelewski", "institution": "UBC"}, {"name": "Madagascar", "institution": "University of Texas at Austin", "homepage": "https://www.reproducibility.org/"}], "url": "https://reproducibility.org/blog/2016/01/16/program-of-the-month-sfsort/", "executable": "sfsort", "io": {"stdin": true, "stdout": true, "stderr": true}, "parameters": [{"type": "enum", "keyword": "ascmode=", "description": "Sort order", "multiple": false, "default": "n", "required": false, "options": [{"description": "ascending", "value": "y"}, {"description": "descending", "value": "n"}]}, {"type": "integer", "keyword": "dim=", "description": "Maximum dimension", "multiple": false, "required": false}, {"type": "integer", "keyword": "memsize=", "description": "Max amount of RAM (in Mb) to be used", "multiple": false, "required": false}]}}]}