{"id": "_pytest.python", "path": "/home/david/mambaforge/envs/jpterm-dev/lib/python3.10/site-packages/_pytest/python.py", "mtime": 1648225782, "size": 69999, "hash": "c2ab6c609e85396ed690cb6085b3b1379858a33c8e2a8277d6b002dff6b4f957", "data_mtime": 1648224604, "dependencies": ["enum", "fnmatch", "inspect", "itertools", "os", "sys", "types", "warnings", "collections", "functools", "pathlib", "typing", "attr", "_pytest", "_pytest.fixtures", "_pytest.nodes", "_pytest._code", "_pytest._code.code", "_pytest._io", "_pytest._io.saferepr", "_pytest.compat", "_pytest.config", "_pytest.config.argparsing", "_pytest.deprecated", "_pytest.main", "_pytest.mark", "_pytest.mark.structures", "_pytest.outcomes", "_pytest.pathlib", "_pytest.scope", "_pytest.warning_types", "typing_extensions", "builtins", "_collections_abc", "_pytest._io.terminalwriter", "_pytest.config.compat", "_pytest.hookspec", "_typeshed", "_warnings", "abc", "argparse", "attr.setters", "posixpath", "py", "py.path"], "suppressed": [], "options": {"follow_imports": "normal", "warn_unreachable": false, "disallow_untyped_defs": false, "platform": "linux", "disallow_incomplete_defs": false, "no_implicit_optional": false, "show_none_errors": true, "warn_no_return": true, "always_true": [], "local_partial_types": false, "strict_optional": true, "disallow_any_explicit": false, "check_untyped_defs": false, "strict_equality": false, "implicit_reexport": true, "strict_optional_whitelist": null, "disallow_untyped_decorators": false, "ignore_missing_imports": false, "allow_untyped_globals": false, "always_false": [], "disallow_any_unimported": false, "mypyc": false, "allow_redefinition": false, "ignore_errors": false, "disallow_subclassing_any": false, "disallow_any_expr": false, "warn_unused_ignores": false, "disallow_any_generics": false, "plugins": [], "warn_return_any": false, "disallow_any_decorated": false, "follow_imports_for_stubs": false, "disallow_untyped_calls": false, "bazel": false}, "dep_prios": [10, 10, 10, 10, 10, 10, 10, 10, 5, 5, 5, 5, 10, 10, 5, 10, 5, 5, 5, 5, 5, 5, 5, 5, 5, 5, 5, 5, 5, 5, 5, 25, 5, 30, 30, 30, 30, 30, 30, 30, 30, 30, 30, 30, 30], "dep_lines": [2, 3, 4, 5, 6, 7, 8, 9, 10, 12, 13, 14, 30, 32, 33, 34, 35, 37, 39, 40, 41, 55, 58, 59, 63, 64, 66, 70, 72, 78, 79, 83, 1, 1, 1, 1, 1, 1, 1, 1, 1, 1, 1, 1, 1], "interface_hash": "dbe7d1f42144a947aee1643660994af84c832f0dd0e33c1c05db1b1b4fce1042", "version_id": "0.942", "ignore_all": true, "plugin_data": null}